collective.xmltestreport-2.0.2-py2.7-nspkg.pth
collective/xmltestreport/__init__.py
collective/xmltestreport/formatter.py
collective/xmltestreport/recipe.py
collective/xmltestreport/runner.py
collective/xmltestreport/utils.py
collective.xmltestreport-2.0.2.dist-info/METADATA
collective.xmltestreport-2.0.2.dist-info/WHEEL
collective.xmltestreport-2.0.2.dist-info/entry_points.txt
collective.xmltestreport-2.0.2.dist-info/namespace_packages.txt
collective.xmltestreport-2.0.2.dist-info/top_level.txt
collective.xmltestreport-2.0.2.dist-info/RECORD
