Metadata-Version: 2.1
Name: collective.xmltestreport
Version: 2.0.2
Summary: A test runner which can output an XML report compatible with JUnit and Jenkins
Home-page: https://pypi.org/project/collective.xmltestreport
Author: Martin Aspeli
Author-email: plone-developers@lists.sourceforge.net
License: ZPL 2.1
Keywords: jenkins junit xml zope.testing
Platform: UNKNOWN
Classifier: Development Status :: 5 - Production/Stable
Classifier: License :: OSI Approved :: Zope Public License
Classifier: Programming Language :: Python
Classifier: Programming Language :: Python :: 2.7
Classifier: Programming Language :: Python :: 3.5
Classifier: Programming Language :: Python :: 3.6
Classifier: Programming Language :: Python :: 3.7
Requires-Dist: setuptools
Requires-Dist: six
Requires-Dist: zope.testing
Requires-Dist: zope.testrunner
Requires-Dist: zc.recipe.egg
